setup.cfg
setup.py
duka/__init__.py
duka/main.py
duka.egg-info/PKG-INFO
duka.egg-info/SOURCES.txt
duka.egg-info/dependency_links.txt
duka.egg-info/entry_points.txt
duka.egg-info/requires.txt
duka.egg-info/top_level.txt
duka/app/__init__.py
duka/app/app.py
duka/core/__init__.py
duka/core/candle.py
duka/core/csv_dumper.py
duka/core/fetch.py
duka/core/processor.py
duka/core/utils.py
duka/tests/__init__.py
duka/tests/test_dates_generator.py
duka/tests/test_find_sunday.py