Metadata-Version: 1.1
Name: duka
Version: 0.2.0
Summary: Dukascopy Bank SA historical data downloader
Home-page: https://github.com/giuse88/duka
Author: Giuseppe Pes
Author-email: giuse88@gmail.com
License: UNKNOWN
Download-URL: https://github.com/giuse88/duka/tarball/0.2.0
Keywords: dukascopy,forex,finance,historical data,price,currency
Platform: UNKNOWN
Classifier: Environment :: Console
Classifier: Programming Language :: Python :: 3.5
Classifier: Programming Language :: Python :: 3 :: Only
Classifier: Development Status :: 4 - Beta
Classifier: Environment :: Other Environment
Classifier: Intended Audience :: Developers
Classifier: Intended Audience :: Financial and Insurance Industry
Classifier: License :: OSI Approved :: MIT License
Classifier: Operating System :: OS Independent
